data_reporter/__init__.py
data_reporter/__main__.py
data_reporter/reporter.py
data_reporter-0.2.dist-info/METADATA
data_reporter-0.2.dist-info/WHEEL
data_reporter-0.2.dist-info/top_level.txt
data_reporter-0.2.dist-info/RECORD
